three_flatline_cli/__init__.py
three_flatline_cli/cli.py
three_flatline_cli-1.4.dist-info/LICENSE
three_flatline_cli-1.4.dist-info/METADATA
three_flatline_cli-1.4.dist-info/WHEEL
three_flatline_cli-1.4.dist-info/entry_points.txt
three_flatline_cli-1.4.dist-info/RECORD
