Metadata-Version: 2.1
Name: three-flatline-cli
Version: 1.4
Summary: CLI for the Dixie vulnerability scanner from 3Flatline
Home-page: https://3flatline.ai
License: Apache 2.0
Author: Adrian Tilston
Author-email: adrian@3flatline.ai
Requires-Python: >=3.10,<4.0
Classifier: License :: Other/Proprietary License
Classifier: Programming Language :: Python :: 3
Classifier: Programming Language :: Python :: 3.10
Classifier: Programming Language :: Python :: 3.11
Classifier: Programming Language :: Python :: 3.12
Requires-Dist: boto3 (>=1.34.23,<2.0.0)
Requires-Dist: botocore (>=1.34.23,<2.0.0)
Requires-Dist: cmd2 (>=2.4.3,<3.0.0)
Requires-Dist: gotrue (>=2.1.0,<3.0.0)
Requires-Dist: pyfiglet (>=1.0.2,<2.0.0)
Requires-Dist: requests (>=2.31.0,<3.0.0)
Requires-Dist: supabase (>=2.3.4,<3.0.0)
Requires-Dist: tiktoken (>=0.5.2,<0.6.0)
Project-URL: Repository, https://github.com/3Flatline/3flatline-public
